vule_magics/__init__.py
vule_magics/_version.py
vule_magics/colab/sparksql.py
vule_magics/sparksql/__init__.py
vule_magics/sparksql/sparksql.py
vule_magics/sparksql/widget.py
vule_magics-1.2.1.data/data/share/jupyter/labextensions/vule-magics/package.json
vule_magics-1.2.1.data/data/share/jupyter/labextensions/vule-magics/static/568.56228813aa0df1f53f88.js
vule_magics-1.2.1.data/data/share/jupyter/labextensions/vule-magics/static/747.6b9eb3eb7bd07ac8fdef.js
vule_magics-1.2.1.data/data/share/jupyter/labextensions/vule-magics/static/remoteEntry.5f7151d68eec31b0044c.js
vule_magics-1.2.1.data/data/share/jupyter/labextensions/vule-magics/static/style.js
vule_magics-1.2.1.data/data/share/jupyter/labextensions/vule-magics/static/third-party-licenses.json
vule_magics-1.2.1.data/data/share/jupyter/labextensions/vule-magics/install.json
vule_magics-1.2.1.dist-info/METADATA
vule_magics-1.2.1.dist-info/WHEEL
vule_magics-1.2.1.dist-info/licenses/LICENSE
vule_magics-1.2.1.dist-info/RECORD
