Metadata-Version: 2.1
Name: vule_magics
Version: 1.2.1
Summary: JupyterLab MagicCommands Extension
Project-URL: Homepage, https://github.com/vule24/vule-jupyter-extensions
Project-URL: Bug Tracker, https://github.com/vule24/vule-jupyter-extensions/issues
Project-URL: Repository, https://github.com/vule24/vule-jupyter-extensions.git
Author-email: Vu Le <ltnv24@gmail.com>
License: BSD 3-Clause License
License-File: LICENSE
Classifier: Framework :: Jupyter
Classifier: Framework :: Jupyter :: JupyterLab
Classifier: Framework :: Jupyter :: JupyterLab :: 3
Classifier: Framework :: Jupyter :: JupyterLab :: Extensions
Classifier: Framework :: Jupyter :: JupyterLab :: Extensions :: Prebuilt
Classifier: License :: OSI Approved :: BSD License
Classifier: Programming Language :: Python
Classifier: Programming Language :: Python :: 3
Classifier: Programming Language :: Python :: 3.7
Classifier: Programming Language :: Python :: 3.8
Classifier: Programming Language :: Python :: 3.9
Classifier: Programming Language :: Python :: 3.10
Classifier: Programming Language :: Python :: 3.11
Requires-Python: >=3.7
Requires-Dist: ipywidgets==7.7.2
Requires-Dist: jupyterlab-widgets==1.1.4
Requires-Dist: pandas
Requires-Dist: plotly
